[
  {
    "invoice_number": "FLI-20260512-001",
    "customer_name": "Nadia Putri",
    "phone": "081234567810",
    "address": "Jl. Kalimantan No. 22, Jember",
    "service": "Cuci Setrika",
    "weight": 4,
    "price_per_unit": 7000,
    "total_price": 28000,
    "payment_status": "Lunas",
    "order_status": "Selesai",
    "notes": "Pisahkan pakaian putih.",
    "created_at": "2026-05-12",
    "estimated_done_at": "2026-05-15",
    "handled_by": "Budi Santoso"
  },
  {
    "invoice_number": "FLI-20260512-002",
    "customer_name": "Rizky Maulana",
    "phone": "081234567811",
    "address": "Jl. Jawa Gang 3, Jember",
    "service": "Express",
    "weight": 3,
    "price_per_unit": 12000,
    "total_price": 36000,
    "payment_status": "DP",
    "order_status": "Diproses",
    "notes": "Butuh malam ini.",
    "created_at": "2026-05-12",
    "estimated_done_at": "2026-05-12",
    "handled_by": "Siti Aminah"
  },
  {
    "invoice_number": "FLI-20260511-003",
    "customer_name": "Ibu Wati",
    "phone": "081234567812",
    "address": "Perum Tegal Besar Permai",
    "service": "Bed Cover",
    "weight": 2,
    "price_per_unit": 25000,
    "total_price": 50000,
    "payment_status": "Belum Bayar",
    "order_status": "Dicuci",
    "notes": "Bed cover ukuran queen.",
    "created_at": "2026-05-11",
    "estimated_done_at": "2026-05-14",
    "handled_by": "Rina Lestari"
  },
  {
    "invoice_number": "FLI-20260510-004",
    "customer_name": "Agus Firmansyah",
    "phone": "081234567813",
    "address": "Jl. Sumatra No. 8, Jember",
    "service": "Cuci Kering",
    "weight": 6,
    "price_per_unit": 5000,
    "total_price": 30000,
    "payment_status": "Lunas",
    "order_status": "Diambil",
    "notes": "",
    "created_at": "2026-05-10",
    "estimated_done_at": "2026-05-12",
    "handled_by": "Budi Santoso"
  },
  {
    "invoice_number": "FLI-20260509-005",
    "customer_name": "Citra Maharani",
    "phone": "081234567814",
    "address": "Jl. Riau No. 17, Jember",
    "service": "Setrika Saja",
    "weight": 5,
    "price_per_unit": 4000,
    "total_price": 20000,
    "payment_status": "Lunas",
    "order_status": "Packing",
    "notes": "Gantung kemeja.",
    "created_at": "2026-05-09",
    "estimated_done_at": "2026-05-10",
    "handled_by": "Siti Aminah"
  },
  {
    "invoice_number": "FLI-20260508-006",
    "customer_name": "Fajar Hidayat",
    "phone": "081234567815",
    "address": "Jl. Mastrip No. 45, Jember",
    "service": "Sepatu",
    "weight": 2,
    "price_per_unit": 30000,
    "total_price": 60000,
    "payment_status": "DP",
    "order_status": "Dijemur",
    "notes": "Sneakers putih.",
    "created_at": "2026-05-08",
    "estimated_done_at": "2026-05-12",
    "handled_by": "Rina Lestari"
  },
  {
    "invoice_number": "FLI-20260507-007",
    "customer_name": "Laras Kusuma",
    "phone": "081234567816",
    "address": "Jl. Gajah Mada No. 5, Jember",
    "service": "Cuci Setrika",
    "weight": 8,
    "price_per_unit": 7000,
    "total_price": 56000,
    "payment_status": "Lunas",
    "order_status": "Dikirim",
    "notes": "Antar sore.",
    "created_at": "2026-05-07",
    "estimated_done_at": "2026-05-10",
    "handled_by": "Budi Santoso"
  },
  {
    "invoice_number": "FLI-20260506-008",
    "customer_name": "Tono Saputra",
    "phone": "081234567817",
    "address": "Jl. Diponegoro No. 2, Jember",
    "service": "Express",
    "weight": 2.5,
    "price_per_unit": 12000,
    "total_price": 30000,
    "payment_status": "Belum Bayar",
    "order_status": "Baru",
    "notes": "Pickup jam 10.",
    "created_at": "2026-05-06",
    "estimated_done_at": "2026-05-06",
    "handled_by": "Siti Aminah"
  },
  {
    "invoice_number": "FLI-20260505-009",
    "customer_name": "Nur Aisyah",
    "phone": "081234567818",
    "address": "Jl. Trunojoyo No. 14, Jember",
    "service": "Cuci Kering",
    "weight": 7,
    "price_per_unit": 5000,
    "total_price": 35000,
    "payment_status": "Lunas",
    "order_status": "Selesai",
    "notes": "",
    "created_at": "2026-05-05",
    "estimated_done_at": "2026-05-07",
    "handled_by": "Rina Lestari"
  },
  {
    "invoice_number": "FLI-20260504-010",
    "customer_name": "Bayu Nugroho",
    "phone": "081234567819",
    "address": "Jl. Letjen Suprapto No. 31, Jember",
    "service": "Bed Cover",
    "weight": 1,
    "price_per_unit": 25000,
    "total_price": 25000,
    "payment_status": "Lunas",
    "order_status": "Disetrika",
    "notes": "Selimut tebal.",
    "created_at": "2026-05-04",
    "estimated_done_at": "2026-05-07",
    "handled_by": "Budi Santoso"
  }
]
